setup.py
cantrips/__init__.py
cantrips/protocol/__init__.py
cantrips/protocol/messaging/__init__.py
cantrips/protocol/messaging/formats.py
cantrips/protocol/tornado/__init__.py
cantrips/protocol/tornado/websocket_server.py
cantrips/protocol/traits/__init__.py
cantrips/protocol/traits/formatteable.py
cantrips/protocol/traits/permcheck.py
cantrips/protocol/traits/provider.py
cantrips/protocol/traits/say.py
cantrips/protocol/traits/whisper.py
cantrips/protocol/traits/decorators/__init__.py
cantrips/protocol/traits/decorators/authcheck.py
cantrips/protocol/traits/decorators/incheck.py
cantrips/protocol/traits/user/__init__.py
cantrips/protocol/traits/user/base.py
cantrips/protocol/traits/user/master.py
cantrips/protocol/traits/user/slave.py
cantrips/protocol/twisted/__init__.py
cantrips/protocol/twisted/server.py
cantrips/protocol/twisted/websocket_server.py
cantrips/task/__init__.py
cantrips/task/audit.py
cantrips/task/features.py
cantrips/task/toll.py
python_server_cantrips.egg-info/PKG-INFO
python_server_cantrips.egg-info/SOURCES.txt
python_server_cantrips.egg-info/dependency_links.txt
python_server_cantrips.egg-info/namespace_packages.txt
python_server_cantrips.egg-info/requires.txt
python_server_cantrips.egg-info/top_level.txt