Metadata-Version: 1.0
Name: python-server-cantrips
Version: 0.0.4
Summary: Python library with small server patterns (i.e. not full protocols/managements, but just small patterns) to integrate a real-time server architecture
Home-page: https://github.com/luismasuelli/python-server-cantrips
Author: Luis y Anita
Author-email: luismasuelli@hotmail.com
License: LGPL
Platform: UNKNOWN
